lymbo/__init__.py
lymbo/__main__.py
lymbo/cm.py
lymbo/collect.py
lymbo/color.py
lymbo/config.py
lymbo/env.py
lymbo/exception.py
lymbo/item.py
lymbo/log.py
lymbo/report.py
lymbo/resource_manager.py
lymbo/run.py
lymbo/utils.py
lymbo-0.3.1.dist-info/licenses/LICENSE
lymbo-0.3.1.dist-info/METADATA
lymbo-0.3.1.dist-info/WHEEL
lymbo-0.3.1.dist-info/entry_points.txt
lymbo-0.3.1.dist-info/top_level.txt
lymbo-0.3.1.dist-info/RECORD
