Metadata-Version: 2.4
Name: lymbo
Version: 0.3.1
Summary: A test runner designed for large test suites and small scripts.
Author-email: cle-b <cle@tictac.pm>
License: Apache-2.0
Project-URL: Source, https://github.com/cle-b/lymbo/
Classifier: Development Status :: 4 - Beta
Classifier: Intended Audience :: Developers
Classifier: License :: OSI Approved :: Apache Software License
Classifier: Operating System :: OS Independent
Classifier: Programming Language :: Python :: 3
Classifier: Programming Language :: Python :: 3.9
Classifier: Programming Language :: Python :: 3.10
Classifier: Programming Language :: Python :: 3.11
Classifier: Programming Language :: Python :: 3.12
Classifier: Topic :: Software Development :: Testing
Classifier: Topic :: Utilities
Requires-Python: >=3.9
License-File: LICENSE
Dynamic: license-file
